vman/__init__.py
vman/_version.py
vman/config.toml
vman/constants.py
vman/logger_conf.json
vman/term_args.py
vman/urls.json
vman/utils.py
vman/vman.py
vman-0.0.37.dist-info/licenses/COPYING
vman-0.0.37.dist-info/licenses/LICENSE
vman-0.0.37.dist-info/METADATA
vman-0.0.37.dist-info/WHEEL
vman-0.0.37.dist-info/entry_points.txt
vman-0.0.37.dist-info/top_level.txt
vman-0.0.37.dist-info/RECORD
