Metadata-Version: 2.4
Name: vman
Version: 0.0.37
Summary: Video Man Pages
Author-email: sivefunc <sivefunc@tuta.io>
License: vman <-> Video Man Pages
Project-URL: Homepage, https://github.com/Sivefunc/vman
Classifier: License :: OSI Approved :: GNU General Public License v3 (GPLv3)
Classifier: Programming Language :: Python
Classifier: Programming Language :: Python :: 3
Requires-Python: >=3.11
License-File: LICENSE
License-File: COPYING
Provides-Extra: dev
Requires-Dist: pylint; extra == "dev"
Provides-Extra: keywords
Requires-Dist: linux; extra == "keywords"
Requires-Dist: python3; extra == "keywords"
Requires-Dist: man; extra == "keywords"
Dynamic: license-file
